CHANGES.txt
LICENSE.txt
MANIFEST.in
README.txt
setup.py
van/__init__.py
van.pg.egg-info/PKG-INFO
van.pg.egg-info/SOURCES.txt
van.pg.egg-info/dependency_links.txt
van.pg.egg-info/namespace_packages.txt
van.pg.egg-info/not-zip-safe
van.pg.egg-info/requires.txt
van.pg.egg-info/top_level.txt
van/pg/README.txt
van/pg/__init__.py
van/pg/_cluster.py
van/pg/tests/__init__.py
van/pg/tests/test_cluster.py