Metadata-Version: 1.0
Name: van.pg
Version: 2.0
Summary: Tools to programmatically manage PostgreSQL clusters as Python test fixtures.
Home-page: UNKNOWN
Author: Brian Sutherland
Author-email: brian@vanguardistas.net
License: BSD
Platform: UNKNOWN
Classifier: Development Status :: 5 - Production/Stable
Classifier: Intended Audience :: Developers
Classifier: Operating System :: OS Independent
Classifier: License :: OSI Approved :: BSD License
Classifier: Topic :: Database
Classifier: Topic :: Software Development :: Testing
Classifier: Programming Language :: Python :: 2
Classifier: Programming Language :: Python :: 2.6
Classifier: Programming Language :: Python :: 2.7
Classifier: Programming Language :: Python :: 3
Classifier: Programming Language :: Python :: 3.2
